get_province_city_county/__init__.py
get_province_city_county/city.py
get_province_city_county/citys.py
get_province_city_county-1.3.0.dist-info/METADATA
get_province_city_county-1.3.0.dist-info/WHEEL
get_province_city_county-1.3.0.dist-info/top_level.txt
get_province_city_county-1.3.0.dist-info/RECORD
