Metadata-Version: 2.1
Name: get-province-city-county
Version: 1.3.0
Summary: 这是一个从文本提取中文地区的包
Home-page: https://github.com/oldlwhite/get_province_city_county
Author: 白旭东
Author-email: 2216403312@qq.com
License: UNKNOWN
Platform: UNKNOWN
Classifier: Programming Language :: Python :: 3
Classifier: License :: OSI Approved :: MIT License
Classifier: Operating System :: OS Independent
Requires-Python: >=3.0
